MANIFEST.in
README.rst
setup.py
docs/conf.py
docs/index.rst
xbob/__init__.py
xbob.db.casia_fasd.egg-info/PKG-INFO
xbob.db.casia_fasd.egg-info/SOURCES.txt
xbob.db.casia_fasd.egg-info/dependency_links.txt
xbob.db.casia_fasd.egg-info/entry_points.txt
xbob.db.casia_fasd.egg-info/namespace_packages.txt
xbob.db.casia_fasd.egg-info/not-zip-safe
xbob.db.casia_fasd.egg-info/requires.txt
xbob.db.casia_fasd.egg-info/top_level.txt
xbob/db/__init__.py
xbob/db/casia_fasd/__init__.py
xbob/db/casia_fasd/driver.py
xbob/db/casia_fasd/models.py
xbob/db/casia_fasd/spoofing.py
xbob/db/casia_fasd/test.py
xbob/db/casia_fasd/face-locations/test_release/1/1.face
xbob/db/casia_fasd/face-locations/test_release/1/2.face
xbob/db/casia_fasd/face-locations/test_release/1/3.face
xbob/db/casia_fasd/face-locations/test_release/1/4.face
xbob/db/casia_fasd/face-locations/test_release/1/5.face
xbob/db/casia_fasd/face-locations/test_release/1/6.face
xbob/db/casia_fasd/face-locations/test_release/1/7.face
xbob/db/casia_fasd/face-locations/test_release/1/8.face
xbob/db/casia_fasd/face-locations/test_release/1/HR_1.face
xbob/db/casia_fasd/face-locations/test_release/1/HR_2.face
xbob/db/casia_fasd/face-locations/test_release/1/HR_3.face
xbob/db/casia_fasd/face-locations/test_release/1/HR_4.face
xbob/db/casia_fasd/face-locations/test_release/10/1.face
xbob/db/casia_fasd/face-locations/test_release/10/2.face
xbob/db/casia_fasd/face-locations/test_release/10/3.face
xbob/db/casia_fasd/face-locations/test_release/10/4.face
xbob/db/casia_fasd/face-locations/test_release/10/5.face
xbob/db/casia_fasd/face-locations/test_release/10/6.face
xbob/db/casia_fasd/face-locations/test_release/10/7.face
xbob/db/casia_fasd/face-locations/test_release/10/8.face
xbob/db/casia_fasd/face-locations/test_release/10/HR_1.face
xbob/db/casia_fasd/face-locations/test_release/10/HR_2.face
xbob/db/casia_fasd/face-locations/test_release/10/HR_3.face
xbob/db/casia_fasd/face-locations/test_release/10/HR_4.face
xbob/db/casia_fasd/face-locations/test_release/11/1.face
xbob/db/casia_fasd/face-locations/test_release/11/2.face
xbob/db/casia_fasd/face-locations/test_release/11/3.face
xbob/db/casia_fasd/face-locations/test_release/11/4.face
xbob/db/casia_fasd/face-locations/test_release/11/5.face
xbob/db/casia_fasd/face-locations/test_release/11/6.face
