Metadata-Version: 1.1
Name: xbob.db.casia-fasd
Version: 1.1.1
Summary: CASIA Face Anti-Spoofing Database Access API for Bob
Home-page: http://pypi.python.org/pypi/xbob.db.casia_fasd
Author: Andre Anjos, Ivana Chingovska
Author-email: andre.anjos@idiap.ch, ivana.chingovska@idiap.ch
License: GPLv3
Platform: UNKNOWN
Classifier: Development Status :: 5 - Production/Stable
Classifier: Intended Audience :: Science/Research
Classifier: License :: OSI Approved :: GNU General Public License v3 (GPLv3)
Classifier: Natural Language :: English
Classifier: Programming Language :: Python
Classifier: Programming Language :: Python :: 3
Classifier: Topic :: Scientific/Engineering :: Artificial Intelligence
Classifier: Topic :: Database :: Front-Ends
